{
  "latest_content_date": "2026-04-18",
  "categories": [
    {
      "key": "ai-news",
      "name": "AIニュース",
      "description": "AI技術、研究、規制、企業動向を中心に扱います。",
      "route": "/ai-news/",
      "latest_date": "2026-04-18",
      "months": [
        {
          "month": "2026-04",
          "route": "/ai-news/2026/04/",
          "dates": [
            "2026-04-18"
          ]
        }
      ]
    },
    {
      "key": "ai-tools-news",
      "name": "AIツールニュース",
      "description": "生成AIツール、業務活用、プロダクト更新を中心に扱います。",
      "route": "/ai-tools-news/",
      "latest_date": "2026-04-18",
      "months": [
        {
          "month": "2026-04",
          "route": "/ai-tools-news/2026/04/",
          "dates": [
            "2026-04-18"
          ]
        }
      ]
    },
    {
      "key": "general-news",
      "name": "一般ニュース",
      "description": "社会、経済、国際、テクノロジー全般の主要ニュースを扱います。",
      "route": "/general-news/",
      "latest_date": "2026-04-18",
      "months": [
        {
          "month": "2026-04",
          "route": "/general-news/2026/04/",
          "dates": [
            "2026-04-18"
          ]
        }
      ]
    }
  ],
  "entries": [
    {
      "category": "ai-news",
      "date": "2026-04-18",
      "month": "2026-04",
      "title": "2026年4月18日 AIニュース解説",
      "summary": "サンプルデータです。AI活用の評価、ガバナンス、現場実装をめぐる論点を日次レポート形式で整理しています。",
      "route": "/ai-news/2026/04/18/",
      "month_route": "/ai-news/2026/04/",
      "top_rank_title": "サンプル：AIモデル評価基準の見直しが進む",
      "ranking_count": 3
    },
    {
      "category": "ai-tools-news",
      "date": "2026-04-18",
      "month": "2026-04",
      "title": "2026年4月18日 AIツールニュース解説",
      "summary": "サンプルデータです。AIツールのチーム利用、ワークフロー連携、レビュー機能に関する話題を整理しています。",
      "route": "/ai-tools-news/2026/04/18/",
      "month_route": "/ai-tools-news/2026/04/",
      "top_rank_title": "サンプル：AI文書作成ツールにチームレビュー機能が追加",
      "ranking_count": 3
    },
    {
      "category": "general-news",
      "date": "2026-04-18",
      "month": "2026-04",
      "title": "2026年4月18日 一般ニュース解説",
      "summary": "サンプルデータです。社会、経済、テクノロジーの横断的な動きを、日次ニュース形式で整理しています。",
      "route": "/general-news/2026/04/18/",
      "month_route": "/general-news/2026/04/",
      "top_rank_title": "サンプル：公共サービスのオンライン手続き拡充が議論に",
      "ranking_count": 3
    }
  ]
}
